addition_umn.py
umn-0.0.1.dist-info/LICENSE
umn-0.0.1.dist-info/METADATA
umn-0.0.1.dist-info/WHEEL
umn-0.0.1.dist-info/top_level.txt
umn-0.0.1.dist-info/RECORD
